prodmatic/__init__.py
prodmatic/appstore/__init__.py
prodmatic/appstore/api.py
prodmatic/appstore/pricing.py
prodmatic/base/__init__.py
prodmatic/base/api.py
prodmatic/base/pricing.py
prodmatic/playstore/__init__.py
prodmatic/playstore/api.py
prodmatic/playstore/pricing.py
prodmatic/resources/appstore_reference_prices.csv
prodmatic/resources/data_sources.json
prodmatic/resources/playstore_reference_prices.csv
prodmatic-2024.5.14.dist-info/LICENSE
prodmatic-2024.5.14.dist-info/METADATA
prodmatic-2024.5.14.dist-info/WHEEL
prodmatic-2024.5.14.dist-info/top_level.txt
prodmatic-2024.5.14.dist-info/RECORD
