Metadata-Version: 2.1
Name: prodmatic
Version: 2024.5.14
Summary: A Python package for seamless management and pricing of in-app products and subscriptions
Home-page: https://github.com/musicmuni/prodmatic
Author: Gopala Krishna Koduri
Author-email: gopal@riyazapp.com
Project-URL: Source Code, https://github.com/musicmuni/prodmatic
Project-URL: Issue Tracker, https://github.com/musicmuni/prodmatic/issues
Project-URL: Connect w/ Author, https://linkedin.com/in/gopalkoduri
Project-URL: Riyaz - Learn to sing, https://riyazapp.com
Classifier: Development Status :: 3 - Alpha
Classifier: Intended Audience :: Developers
Classifier: Topic :: Software Development :: Libraries
Classifier: License :: OSI Approved :: GNU Affero General Public License v3
Classifier: Programming Language :: Python :: 3
Classifier: Programming Language :: Python :: 3.7
Classifier: Programming Language :: Python :: 3.8
Classifier: Programming Language :: Python :: 3.9
Classifier: Programming Language :: Python :: 3.10
Classifier: Programming Language :: Python :: 3.11
License-File: LICENSE
Requires-Dist: requests
Requires-Dist: beautifulsoup4
Requires-Dist: pyrestcountries
Requires-Dist: pppfy
Requires-Dist: moneymatters
